{
  "$schema": "http://json-schema.org/draft-07/schema#",
  "type": "object",
  "properties": {
    "z_year_month": {
      "type": ["null", "string"]
    },
    "product_no": {
      "type": ["null", "string"]
    },
    "product_name": {
      "type": ["null", "string"]
    },
    "logical_node_no": {
      "type": ["null", "string"]
    },
    "logical_node_name": {
      "type": ["null", "string"]
    },
    "z_plan_prod_qty": {
      "type": ["null", "string", "number"]
    },
    "prod_distribute_type": {
      "type": ["null", "string"]
    }
  }
}
